pracklrsec/__init__.py
pracklrsec/pracklrsec.py
pracklrsec-0.1.dist-info/METADATA
pracklrsec-0.1.dist-info/WHEEL
pracklrsec-0.1.dist-info/top_level.txt
pracklrsec-0.1.dist-info/RECORD
